raspinet/__init__.py
raspinet/chat.py
raspinet/core.py
raspinet-0.1.0.dist-info/LICENSE
raspinet-0.1.0.dist-info/METADATA
raspinet-0.1.0.dist-info/WHEEL
raspinet-0.1.0.dist-info/RECORD
